django_reset_migrations-0.3.0.dist-info/DESCRIPTION.rst
django_reset_migrations-0.3.0.dist-info/METADATA
django_reset_migrations-0.3.0.dist-info/RECORD
django_reset_migrations-0.3.0.dist-info/WHEEL
django_reset_migrations-0.3.0.dist-info/metadata.json
django_reset_migrations-0.3.0.dist-info/top_level.txt
reset_migrations/__init__.py
reset_migrations/management/__init__.py
reset_migrations/management/commands/__init__.py
reset_migrations/management/commands/reset_migrations.py
